Workbook

Sheet Допущения
A1: Параметр | B1: Значение | C1: Единица | D1: Комментарии
A2: Средний чек | B2: 25 | C2: USD | D2: Допущение
A3: Заказов на пользователя | B3: 2.4 | C3: шт/год | D3: Условное
A4: PSP с конвертацией | B4: 0.024 | C4: доля GMV | D4: Порог CFO строго ниже 2,5%, тариф не подтверждён
A5: Логистика на заказ | B5: 1.2 | C5: USD | D5: Платформенная часть, не вся перевозка
A6: Сообщения на заказ | B6: 0.035 | C6: USD | D6: Только с правовым основанием
A7: Рост инфраструктуры | B7: 0.13 | C7: доля | D7: Модель
A8: Рост ФОТ | B8: 0.06 | C8: доля | D8: Модель
A9: Инфляция | B9: 0.04 | C9: доля | D9: Модель
A10: Ставка дисконтирования | B10: 0.15 | C10: доля | D10: Модель
A11: FTE в месяц | B11: 3500 | C11: USD | D11: Условная полная стоимость контрактора
A12: Compliance Y1 | B12: 20000 | C12: USD | D12: Оценка
A13: Compliance Y2+ | B13: 7000 | C13: USD | D13: Оценка
... A16: CFO лимит | B16: 5000 | C16: USD/мес | D16: Первые 6 месяцев
A19: Год | B19: Y1 | C19: Y2 | D19: Y3 | E19: Y4 | F19: Y5
A20: Пользователи | B20: 50000 | C20: 120000 | D20: 250000 | E20: 500000 | F20: 1000000
A21: Заказы | B21: =B20*$B$3 -> 0 | C21: =C20*$B$3 -> 0 | D21: =D20*$B$3 -> 0 | E21: =E20*$B$3 -> 0 | F21: =F20*$B$3 -> 0
A22: GMV | B22: =B21*$B$2 -> 0 | C22: =C21*$B$2 -> 0 | D22: =D21*$B$2 -> 0 | E22: =E21*$B$2 -> 0 | F22: =F21*$B$2 -> 0
A24: Все тарифы гипотетические, не договорные; input Task1 C-01/C-07.
A26: Второй локальный контур NG/KE, USD/мес. | B26: 1700
A27: Внутристрановое резервирование, USD/мес. | B27: 500
A28: Суммарное дополнительное размещение, USD/мес. | B28: =SUM(B26:B27) -> 0
A29: Статус: смета не подтверждена; обязательна проверка ЦОД NG/KE и CFO.

Sheet A Монолит
A1: A Монолит | TCO 5 лет (USD)
A3: Показатель | B3: Y1 | C3: Y2 | D3: Y3 | E3: Y4 | F3: Y5
A4: Пользователи | B4: ='Допущения'!B20 -> 0 | C4: ='Допущения'!C20 -> 0 | D4: ='Допущения'!D20 -> 0 | E4: ='Допущения'!E20 -> 0 | F4: ='Допущения'!F20 -> 0
A5: Заказы | B5: ='Допущения'!B21 -> 0 | C5: ='Допущения'!C21 -> 0 | D5: ='Допущения'!D21 -> 0 | E5: ='Допущения'!E21 -> 0 | F5: ='Допущения'!F21 -> 0
A6: GMV | B6: ='Допущения'!B22 -> 0 | C6: ='Допущения'!C22 -> 0 | D6: ='Допущения'!D22 -> 0 | E6: ='Допущения'!E22 -> 0 | F6: ='Допущения'!F22 -> 0
A8: Infra + SaaS | B8: =2600*12*(1+'Допущения'!$B$7)^0 -> 0 | C8: =2600*12*(1+'Допущения'!$B$7)^1 -> 0 | D8: =2600*12*(1+'Допущения'!$B$7)^2 -> 0 | E8: =2600*12*(1+'Допущения'!$B$7)^3 -> 0 | F8: =2600*12*(1+'Допущения'!$B$7)^4 -> 0
A9: Команда/FTE | B9: =6*'Допущения'!$B$11*12*(1+'Допущения'!$B$8)^0 -> 0 | C9: =6*'Допущения'!$B$11*12*(1+'Допущения'!$B$8)^1 -> 0 | D9: =6*'Допущения'!$B$11*12*(1+'Допущения'!$B$8)^2 -> 0 | E9: =6*'Допущения'!$B$11*12*(1+'Допущения'!$B$8)^3 -> 0 | F9: =6*'Допущения'!$B$11*12*(1+'Допущения'!$B$8)^4 -> 0
A10: PSP+FX | B10: =B6*'Допущения'!$B$4 -> 0 | C10: =C6*'Допущения'!$B$4 -> 0 | D10: =D6*'Допущения'!$B$4 -> 0 | E10: =E6*'Допущения'!$B$4 -> 0 | F10: =F6*'Допущения'!$B$4 -> 0
A11: Доставка | B11: =B5*'Допущения'!$B$5 -> 0 | C11: =C5*'Допущения'!$B$5 -> 0 | D11: =D5*'Допущения'!$B$5 -> 0 | E11: =E5*'Допущения'!$B$5 -> 0 | F11: =F5*'Допущения'!$B$5 -> 0
A12: Уведомления | B12: =B5*'Допущения'!$B$6 -> 0 | C12: =C5*'Допущения'!$B$6 -> 0 | D12: =D5*'Допущения'!$B$6 -> 0 | E12: =E5*'Допущения'!$B$6 -> 0 | F12: =F5*'Допущения'!$B$6 -> 0
A13: Compliance | B13: ='Допущения'!$B$12 -> 0 | C13: ='Допущения'!$B$13*(1+'Допущения'!$B$9)^1 -> 0 | D13: ='Допущения'!$B$13*(1+'Допущения'!$B$9)^2 -> 0 | E13: ='Допущения'!$B$13*(1+'Допущения'!$B$9)^3 -> 0 | F13: ='Допущения'!$B$13*(1+'Допущения'!$B$9)^4 -> 0
A14: Внедрение | B14: 6000 | C14: 0 | D14: 0 | E14: 0 | F14: 0
A15: Всего TCO | B15: =SUM(B8:B14) -> 0 | C15: =SUM(C8:C14) -> 0 | D15: =SUM(D8:D14) -> 0 | E15: =SUM(E8:E14) -> 0 | F15: =SUM(F8:F14) -> 0
A16: Технические расходы (infra+люди+legal+setup) | B16: =B8+B9+B13+B14 -> 0 | C16: =C8+C9+C13+C14 -> 0 | D16: =D8+D9+D13+D14 -> 0 | E16: =E8+E9+E13+E14 -> 0 | F16: =F8+F9+F13+F14 -> 0
A17: TCO / заказ | B17: =B15/B5 -> 0 | C17: =C15/C5 -> 0 | D17: =D15/D5 -> 0 | E17: =E15/E5 -> 0 | F17: =F15/F5 -> 0
A18: Tech cost / заказ | B18: =B16/B5 -> 0 | C18: =C16/C5 -> 0 | D18: =D16/D5 -> 0 | E18: =E16/E5 -> 0 | F18: =F16/F5 -> 0
A19: NPV годовой | B19: =B15/(1+'Допущения'!$B$10)^1 -> 0 | C19: =C15/(1+'Допущения'!$B$10)^2 -> 0 | D19: =D15/(1+'Допущения'!$B$10)^3 -> 0 | E19: =E15/(1+'Допущения'!$B$10)^4 -> 0 | F19: =F15/(1+'Допущения'!$B$10)^5 -> 0
A21: TCO 5 лет | B21: =SUM(B15:F15) -> 0
A22: NPV 5 лет | B22: =SUM(B19:F19) -> 0
A23: Стоимость заказа за 5 лет | B23: =B21/SUM(B5:F5) -> 0
A24: Избыточные fixed costs относительно A за 5 лет | B24: =SUM(B8:F9)+SUM(B13:F14)-SUM('A Монолит'!B8:F9)-SUM('A Монолит'!B13:F14) -> 0
A25: Monthly infra+SaaS при старте | B25: =B8/12 -> 0
A26: CFO cap (1=pass) | B26: =IF(B25<='Допущения'!$B$16,1,0) -> 0
A27: FTE | B27: 6
A28: Плановая цена миграции к 10M (НЕ baseline) | B28: 50000
A30: SLO стресс-допущение | B30: ='Допущения'!$B$15 -> 0 | C30: ='Допущения'!$B$15 -> 0 | D30: ='Допущения'!$B$15 -> 0 | E30: ='Допущения'!$B$15 -> 0 | F30: ='Допущения'!$B$15 -> 0
A31: Минут простоя при SLO / год | B31: =(1-B30)*365*24*60 -> 0 | C31: =(1-C30)*365*24*60 -> 0 | D31: =(1-D30)*365*24*60 -> 0 | E31: =(1-E30)*365*24*60 -> 0 | F31: =(1-F30)*365*24*60 -> 0
A32: Гипотетические потери / год | B32: =B31*'Допущения'!$B$14 -> 0 | C32: =C31*'Допущения'!$B$14 -> 0 | D32: =D31*'Допущения'!$B$14 -> 0 | E32: =E31*'Допущения'!$B$14 -> 0 | F32: =F31*'Допущения'!$B$14 -> 0
A33: TCO с условной стоимостью простоя | B33: =B15+B32 -> 0 | C33: =C15+C32 -> 0 | D33: =D15+D32 -> 0 | E33: =E15+E32 -> 0 | F33: =F15+F32 -> 0
A35: B24 = разница фиксированных затрат относительно A (не сумма списаний); объём заказов на неё не влияет.
A36: Сценарий 10M: резерв B28 не включён в baseline; нужна проверка нагрузки и коммерческих тарифов.
A37: TCO и потери при SLO показаны отдельно, без смешения cash cost с модельным ущербом.

Sheet B Сервисы
A1: B Сервисы | TCO 5 лет (USD)
A3: Показатель | B3: Y1 | C3: Y2 | D3: Y3 | E3: Y4 | F3: Y5
A4: Пользователи | B4: ='Допущения'!B20 -> 0 | C4: ='Допущения'!C20 -> 0 | D4: ='Допущения'!D20 -> 0 | E4: ='Допущения'!E20 -> 0 | F4: ='Допущения'!F20 -> 0
A5: Заказы | B5: ='Допущения'!B21 -> 0 | C5: ='Допущения'!C21 -> 0 | D5: ='Допущения'!D21 -> 0 | E5: ='Допущения'!E21 -> 0 | F5: ='Допущения'!F21 -> 0
A6: GMV | B6: ='Допущения'!B22 -> 0 | C6: ='Допущения'!C22 -> 0 | D6: ='Допущения'!D22 -> 0 | E6: ='Допущения'!E22 -> 0 | F6: ='Допущения'!F22 -> 0
A8: Infra + SaaS | B8: =4700*12*(1+'Допущения'!$B$7)^0 -> 0 | C8: =4700*12*(1+'Допущения'!$B$7)^1 -> 0 | D8: =4700*12*(1+'Допущения'!$B$7)^2 -> 0 | E8: =4700*12*(1+'Допущения'!$B$7)^3 -> 0 | F8: =4700*12*(1+'Допущения'!$B$7)^4 -> 0
A9: Команда/FTE | B9: =9*'Допущения'!$B$11*12*(1+'Допущения'!$B$8)^0 -> 0 | C9: =9*'Допущения'!$B$11*12*(1+'Допущения'!$B$8)^1 -> 0 | D9: =9*'Допущения'!$B$11*12*(1+'Допущения'!$B$8)^2 -> 0 | E9: =9*'Допущения'!$B$11*12*(1+'Допущения'!$B$8)^3 -> 0 | F9: =9*'Допущения'!$B$11*12*(1+'Допущения'!$B$8)^4 -> 0
A10: PSP+FX | B10: =B6*'Допущения'!$B$4 -> 0 | C10: =C6*'Допущения'!$B$4 -> 0 | D10: =D6*'Допущения'!$B$4 -> 0 | E10: =E6*'Допущения'!$B$4 -> 0 | F10: =F6*'Допущения'!$B$4 -> 0
A11: Доставка | B11: =B5*'Допущения'!$B$5 -> 0 | C11: =C5*'Допущения'!$B$5 -> 0 | D11: =D5*'Допущения'!$B$5 -> 0 | E11: =E5*'Допущения'!$B$5 -> 0 | F11: =F5*'Допущения'!$B$5 -> 0
A12: Уведомления | B12: =B5*'Допущения'!$B$6 -> 0 | C12: =C5*'Допущения'!$B$6 -> 0 | D12: =D5*'Допущения'!$B$6 -> 0 | E12: =E5*'Допущения'!$B$6 -> 0 | F12: =F5*'Допущения'!$B$6 -> 0
A13: Compliance | B13: ='Допущения'!$B$12 -> 0 | C13: ='Допущения'!$B$13*(1+'Допущения'!$B$9)^1 -> 0 | D13: ='Допущения'!$B$13*(1+'Допущения'!$B$9)^2 -> 0 | E13: ='Допущения'!$B$13*(1+'Допущения'!$B$9)^3 -> 0 | F13: ='Допущения'!$B$13*(1+'Допущения'!$B$9)^4 -> 0
A14: Внедрение | B14: 18000 | C14: 0 | D14: 0 | E14: 0 | F14: 0
A15: Всего TCO | B15: =SUM(B8:B14) -> 0 | C15: =SUM(C8:C14) -> 0 | D15: =SUM(D8:D14) -> 0 | E15: =SUM(E8:E14) -> 0 | F15: =SUM(F8:F14) -> 0
A16: Технические расходы (infra+люди+legal+setup) | B16: =B8+B9+B13+B14 -> 0 | C16: =C8+C9+C13+C14 -> 0 | D16: =D8+D9+D13+D14 -> 0 | E16: =E8+E9+E13+E14 -> 0 | F16: =F8+F9+F13+F14 -> 0
A17: TCO / заказ | B17: =B15/B5 -> 0 | C17: =C15/C5 -> 0 | D17: =D15/D5 -> 0 | E17: =E15/E5 -> 0 | F17: =F15/F5 -> 0
A18: Tech cost / заказ | B18: =B16/B5 -> 0 | C18: =C16/C5 -> 0 | D18: =D16/D5 -> 0 | E18: =E16/E5 -> 0 | F18: =F16/F5 -> 0
A19: NPV годовой | B19: =B15/(1+'Допущения'!$B$10)^1 -> 0 | C19: =C15/(1+'Допущения'!$B$10)^2 -> 0 | D19: =D15/(1+'Допущения'!$B$10)^3 -> 0 | E19: =E15/(1+'Допущения'!$B$10)^4 -> 0 | F19: =F15/(1+'Допущения'!$B$10)^5 -> 0
A21: TCO 5 лет | B21: =SUM(B15:F15) -> 0
A22: NPV 5 лет | B22: =SUM(B19:F19) -> 0
A23: Стоимость заказа за 5 лет | B23: =B21/SUM(B5:F5) -> 0
A24: Избыточные fixed costs относительно A за 5 лет | B24: =SUM(B8:F9)+SUM(B13:F14)-SUM('A Монолит'!B8:F9)-SUM('A Монолит'!B13:F14) -> 0
A25: Monthly infra+SaaS при старте | B25: =B8/12 -> 0
A26: CFO cap (1=pass) | B26: =IF(B25<='Допущения'!$B$16,1,0) -> 0
A27: FTE | B27: 9
A28: Плановая цена миграции к 10M (НЕ baseline) | B28: 100000
A30: SLO стресс-допущение | B30: ='Допущения'!$B$15 -> 0 | C30: ='Допущения'!$B$15 -> 0 | D30: ='Допущения'!$B$15 -> 0 | E30: ='Допущения'!$B$15 -> 0 | F30: ='Допущения'!$B$15 -> 0
A31: Минут простоя при SLO / год | B31: =(1-B30)*365*24*60 -> 0 | C31: =(1-C30)*365*24*60 -> 0 | D31: =(1-D30)*365*24*60 -> 0 | E31: =(1-E30)*365*24*60 -> 0 | F31: =(1-F30)*365*24*60 -> 0
A32: Гипотетические потери / год | B32: =B31*'Допущения'!$B$14 -> 0 | C32: =C31*'Допущения'!$B$14 -> 0 | D32: =D31*'Допущения'!$B$14 -> 0 | E32: =E31*'Допущения'!$B$14 -> 0 | F32: =F31*'Допущения'!$B$14 -> 0
A33: TCO с условной стоимостью простоя | B33: =B15+B32 -> 0 | C33: =C15+C32 -> 0 | D33: =D15+D32 -> 0 | E33: =E15+E32 -> 0 | F33: =F15+F32 -> 0
A35: B24 = разница фиксированных затрат относительно A (не сумма списаний); объём заказов на неё не влияет.
A36: Сценарий 10M: резерв B28 не включён в baseline; нужна проверка нагрузки и коммерческих тарифов.
A37: TCO и потери при SLO показаны отдельно, без смешения cash cost с модельным ущербом.

Sheet C CTO
A1: C CTO | TCO 5 лет (USD)
A3: Показатель | B3: Y1 | C3: Y2 | D3: Y3 | E3: Y4 | F3: Y5
A4: Пользователи | B4: ='Допущения'!B20 -> 0 | C4: ='Допущения'!C20 -> 0 | D4: ='Допущения'!D20 -> 0 | E4: ='Допущения'!E20 -> 0 | F4: ='Допущения'!F20 -> 0
A5: Заказы | B5: ='Допущения'!B21 -> 0 | C5: ='Допущения'!C21 -> 0 | D5: ='Допущения'!D21 -> 0 | E5: ='Допущения'!E21 -> 0 | F5: ='Допущения'!F21 -> 0
A6: GMV | B6: ='Допущения'!B22 -> 0 | C6: ='Допущения'!C22 -> 0 | D6: ='Допущения'!D22 -> 0 | E6: ='Допущения'!E22 -> 0 | F6: ='Допущения'!F22 -> 0
A8: Infra + SaaS | B8: =18500*12*(1+'Допущения'!$B$7)^0 -> 0 | C8: =18500*12*(1+'Допущения'!$B$7)^1 -> 0 | D8: =18500*12*(1+'Допущения'!$B$7)^2 -> 0 | E8: =18500*12*(1+'Допущения'!$B$7)^3 -> 0 | F8: =18500*12*(1+'Допущения'!$B$7)^4 -> 0
A9: Команда/FTE | B9: =18*'Допущения'!$B$11*12*(1+'Допущения'!$B$8)^0 -> 0 | C9: =18*'Допущения'!$B$11*12*(1+'Допущения'!$B$8)^1 -> 0 | D9: =18*'Допущения'!$B$11*12*(1+'Допущения'!$B$8)^2 -> 0 | E9: =18*'Допущения'!$B$11*12*(1+'Допущения'!$B$8)^3 -> 0 | F9: =18*'Допущения'!$B$11*12*(1+'Допущения'!$B$8)^4 -> 0
A10: PSP+FX | B10: =B6*'Допущения'!$B$4 -> 0 | C10: =C6*'Допущения'!$B$4 -> 0 | D10: =D6*'Допущения'!$B$4 -> 0 | E10: =E6*'Допущения'!$B$4 -> 0 | F10: =F6*'Допущения'!$B$4 -> 0
A11: Доставка | B11: =B5*'Допущения'!$B$5 -> 0 | C11: =C5*'Допущения'!$B$5 -> 0 | D11: =D5*'Допущения'!$B$5 -> 0 | E11: =E5*'Допущения'!$B$5 -> 0 | F11: =F5*'Допущения'!$B$5 -> 0
A12: Уведомления | B12: =B5*'Допущения'!$B$6 -> 0 | C12: =C5*'Допущения'!$B$6 -> 0 | D12: =D5*'Допущения'!$B$6 -> 0 | E12: =E5*'Допущения'!$B$6 -> 0 | F12: =F5*'Допущения'!$B$6 -> 0
A13: Compliance | B13: ='Допущения'!$B$12 -> 0 | C13: ='Допущения'!$B$13*(1+'Допущения'!$B$9)^1 -> 0 | D13: ='Допущения'!$B$13*(1+'Допущения'!$B$9)^2 -> 0 | E13: ='Допущения'!$B$13*(1+'Допущения'!$B$9)^3 -> 0 | F13: ='Допущения'!$B$13*(1+'Допущения'!$B$9)^4 -> 0
A14: Внедрение | B14: 80000 | C14: 0 | D14: 0 | E14: 0 | F14: 0
A15: Всего TCO | B15: =SUM(B8:B14) -> 0 | C15: =SUM(C8:C14) -> 0 | D15: =SUM(D8:D14) -> 0 | E15: =SUM(E8:E14) -> 0 | F15: =SUM(F8:F14) -> 0
A16: Технические расходы (infra+люди+legal+setup) | B16: =B8+B9+B13+B14 -> 0 | C16: =C8+C9+C13+C14 -> 0 | D16: =D8+D9+D13+D14 -> 0 | E16: =E8+E9+E13+E14 -> 0 | F16: =F8+F9+F13+F14 -> 0
A17: TCO / заказ | B17: =B15/B5 -> 0 | C17: =C15/C5 -> 0 | D17: =D15/D5 -> 0 | E17: =E15/E5 -> 0 | F17: =F15/F5 -> 0
A18: Tech cost / заказ | B18: =B16/B5 -> 0 | C18: =C16/C5 -> 0 | D18: =D16/D5 -> 0 | E18: =E16/E5 -> 0 | F18: =F16/F5 -> 0
A19: NPV годовой | B19: =B15/(1+'Допущения'!$B$10)^1 -> 0 | C19: =C15/(1+'Допущения'!$B$10)^2 -> 0 | D19: =D15/(1+'Допущения'!$B$10)^3 -> 0 | E19: =E15/(1+'Допущения'!$B$10)^4 -> 0 | F19: =F15/(1+'Допущения'!$B$10)^5 -> 0
A21: TCO 5 лет | B21: =SUM(B15:F15) -> 0
A22: NPV 5 лет | B22: =SUM(B19:F19) -> 0
A23: Стоимость заказа за 5 лет | B23: =B21/SUM(B5:F5) -> 0
A24: Избыточные fixed costs относительно A за 5 лет | B24: =SUM(B8:F9)+SUM(B13:F14)-SUM('A Монолит'!B8:F9)-SUM('A Монолит'!B13:F14) -> 0
A25: Monthly infra+SaaS при старте | B25: =B8/12 -> 0
A26: CFO cap (1=pass) | B26: =IF(B25<='Допущения'!$B$16,1,0) -> 0
A27: FTE | B27: 18
A28: Плановая цена миграции к 10M (НЕ baseline) | B28: 250000
A30: SLO стресс-допущение | B30: ='Допущения'!$B$15 -> 0 | C30: ='Допущения'!$B$15 -> 0 | D30: ='Допущения'!$B$15 -> 0 | E30: ='Допущения'!$B$15 -> 0 | F30: ='Допущения'!$B$15 -> 0
A31: Минут простоя при SLO / год | B31: =(1-B30)*365*24*60 -> 0 | C31: =(1-C30)*365*24*60 -> 0 | D31: =(1-D30)*365*24*60 -> 0 | E31: =(1-E30)*365*24*60 -> 0 | F31: =(1-F30)*365*24*60 -> 0
A32: Гипотетические потери / год | B32: =B31*'Допущения'!$B$14 -> 0 | C32: =C31*'Допущения'!$B$14 -> 0 | D32: =D31*'Допущения'!$B$14 -> 0 | E32: =E31*'Допущения'!$B$14 -> 0 | F32: =F31*'Допущения'!$B$14 -> 0
A33: TCO с условной стоимостью простоя | B33: =B15+B32 -> 0 | C33: =C15+C32 -> 0 | D33: =D15+D32 -> 0 | E33: =E15+E32 -> 0 | F33: =F15+F32 -> 0
A35: B24 = разница фиксированных затрат относительно A (не сумма списаний); объём заказов на неё не влияет.
A36: Сценарий 10M: резерв B28 не включён в baseline; нужна проверка нагрузки и коммерческих тарифов.
A37: TCO и потери при SLO показаны отдельно, без смешения cash cost с модельным ущербом.

Sheet Сценарии 50k 10M
A1: Сценарий | B1: A Монолит | C1: B Сервисы | D1: C CTO
A2: 5-летняя фиксированная разница относительно A, USD | B2: ='A Монолит'!B24 -> 0 | C2: ='B Сервисы'!B24 -> 0 | D2: ='C CTO'!B24 -> 0
A3: Сценарий: 50 000 пользователей в каждый год
A4: Заказы в год при 2,4 заказа/пользователя | B4: =50000*'Допущения'!B3 -> 0
A5: Сценарий: 10 млн пользователей, гипотеза, НЕ проверенная нагрузка
A6: Заказы в год при 2,4 заказа/пользователя | B6: =10000000*'Допущения'!B3 -> 0
A7: Условная стоимость миграции при 10 млн (не baseline) | B7: ='A Монолит'!B28 -> 0 | C7: ='B Сервисы'!B28 -> 0 | D7: ='C CTO'!B28 -> 0
A9: Ни 50 тыс., ни 10 млн не являются фактическим прогнозом. Фиксированные затраты при 50 тыс. остаются, но не обязательно потеряны.
